[
  {
    "Month": "2020-01",
    "Python(%)": 71,
    "JavaScript(%)": 33,
    "Java(%)": 16,
    "C#(%)": 42,
    "PhP(%)": 18,
    "Flutter(%)": 37,
    "React(%)": 61,
    "Swift(%)": 25,
    "TypeScript(%)": 46,
    "Matlab(%)": 46
  },
  {
    "Month": "2020-02",
    "Python(%)": 76,
    "JavaScript(%)": 37,
    "Java(%)": 17,
    "C#(%)": 45,
    "PhP(%)": 19,
    "Flutter(%)": 41,
    "React(%)": 65,
    "Swift(%)": 31,
    "TypeScript(%)": 51,
    "Matlab(%)": 53
  },
  {
    "Month": "2020-03",
    "Python(%)": 69,
    "JavaScript(%)": 34,
    "Java(%)": 15,
    "C#(%)": 41,
    "PhP(%)": 16,
    "Flutter(%)": 41,
    "React(%)": 62,
    "Swift(%)": 23,
    "TypeScript(%)": 49,
    "Matlab(%)": 50
  },
  {
    "Month": "2020-04",
    "Python(%)": 72,
    "JavaScript(%)": 35,
    "Java(%)": 15,
    "C#(%)": 37,
    "PhP(%)": 16,
    "Flutter(%)": 48,
    "React(%)": 64,
    "Swift(%)": 23,
    "TypeScript(%)": 50,
    "Matlab(%)": 51
  },
  {
    "Month": "2020-05",
    "Python(%)": 70,
    "JavaScript(%)": 33,
    "Java(%)": 14,
    "C#(%)": 35,
    "PhP(%)": 16,
    "Flutter(%)": 50,
    "React(%)": 66,
    "Swift(%)": 24,
    "TypeScript(%)": 49,
    "Matlab(%)": 50
  },
  {
    "Month": "2020-06",
    "Python(%)": 66,
    "JavaScript(%)": 34,
    "Java(%)": 14,
    "C#(%)": 38,
    "PhP(%)": 16,
    "Flutter(%)": 49,
    "React(%)": 65,
    "Swift(%)": 25,
    "TypeScript(%)": 53,
    "Matlab(%)": 48
  },
  {
    "Month": "2020-07",
    "Python(%)": 68,
    "JavaScript(%)": 34,
    "Java(%)": 13,
    "C#(%)": 38,
    "PhP(%)": 17,
    "Flutter(%)": 53,
    "React(%)": 67,
    "Swift(%)": 34,
    "TypeScript(%)": 53,
    "Matlab(%)": 43
  },
  {
    "Month": "2020-08",
    "Python(%)": 68,
    "JavaScript(%)": 33,
    "Java(%)": 13,
    "C#(%)": 34,
    "PhP(%)": 16,
    "Flutter(%)": 49,
    "React(%)": 52,
    "Swift(%)": 29,
    "TypeScript(%)": 48,
    "Matlab(%)": 44
  },
  {
    "Month": "2020-09",
    "Python(%)": 71,
    "JavaScript(%)": 33,
    "Java(%)": 16,
    "C#(%)": 38,
    "PhP(%)": 15,
    "Flutter(%)": 48,
    "React(%)": 55,
    "Swift(%)": 27,
    "TypeScript(%)": 50,
    "Matlab(%)": 53
  },
  {
    "Month": "2020-10",
    "Python(%)": 61,
    "JavaScript(%)": 28,
    "Java(%)": 13,
    "C#(%)": 33,
    "PhP(%)": 14,
    "Flutter(%)": 40,
    "React(%)": 41,
    "Swift(%)": 24,
    "TypeScript(%)": 37,
    "Matlab(%)": 51
  },
  {
    "Month": "2020-11",
    "Python(%)": 56,
    "JavaScript(%)": 25,
    "Java(%)": 12,
    "C#(%)": 30,
    "PhP(%)": 13,
    "Flutter(%)": 39,
    "React(%)": 35,
    "Swift(%)": 24,
    "TypeScript(%)": 34,
    "Matlab(%)": 49
  },
  {
    "Month": "2020-12",
    "Python(%)": 53,
    "JavaScript(%)": 24,
    "Java(%)": 12,
    "C#(%)": 28,
    "PhP(%)": 13,
    "Flutter(%)": 39,
    "React(%)": 37,
    "Swift(%)": 33,
    "TypeScript(%)": 34,
    "Matlab(%)": 44
  },
  {
    "Month": "2021-01",
    "Python(%)": 54,
    "JavaScript(%)": 24,
    "Java(%)": 11,
    "C#(%)": 29,
    "PhP(%)": 13,
    "Flutter(%)": 40,
    "React(%)": 41,
    "Swift(%)": 24,
    "TypeScript(%)": 31,
    "Matlab(%)": 42
  },
  {
    "Month": "2021-02",
    "Python(%)": 59,
    "JavaScript(%)": 25,
    "Java(%)": 13,
    "C#(%)": 32,
    "PhP(%)": 14,
    "Flutter(%)": 40,
    "React(%)": 47,
    "Swift(%)": 26,
    "TypeScript(%)": 37,
    "Matlab(%)": 50
  },
  {
    "Month": "2021-03",
    "Python(%)": 60,
    "JavaScript(%)": 28,
    "Java(%)": 14,
    "C#(%)": 34,
    "PhP(%)": 14,
    "Flutter(%)": 51,
    "React(%)": 45,
    "Swift(%)": 28,
    "TypeScript(%)": 37,
    "Matlab(%)": 53
  },
  {
    "Month": "2021-04",
    "Python(%)": 60,
    "JavaScript(%)": 28,
    "Java(%)": 12,
    "C#(%)": 32,
    "PhP(%)": 13,
    "Flutter(%)": 46,
    "React(%)": 44,
    "Swift(%)": 27,
    "TypeScript(%)": 38,
    "Matlab(%)": 50
  },
  {
    "Month": "2021-05",
    "Python(%)": 58,
    "JavaScript(%)": 26,
    "Java(%)": 12,
    "C#(%)": 30,
    "PhP(%)": 13,
    "Flutter(%)": 48,
    "React(%)": 44,
    "Swift(%)": 23,
    "TypeScript(%)": 37,
    "Matlab(%)": 45
  },
  {
    "Month": "2021-06",
    "Python(%)": 59,
    "JavaScript(%)": 28,
    "Java(%)": 12,
    "C#(%)": 34,
    "PhP(%)": 14,
    "Flutter(%)": 49,
    "React(%)": 48,
    "Swift(%)": 23,
    "TypeScript(%)": 43,
    "Matlab(%)": 45
  },
  {
    "Month": "2021-07",
    "Python(%)": 55,
    "JavaScript(%)": 28,
    "Java(%)": 12,
    "C#(%)": 30,
    "PhP(%)": 19,
    "Flutter(%)": 48,
    "React(%)": 49,
    "Swift(%)": 24,
    "TypeScript(%)": 43,
    "Matlab(%)": 43
  },
  {
    "Month": "2021-08",
    "Python(%)": 54,
    "JavaScript(%)": 26,
    "Java(%)": 11,
    "C#(%)": 29,
    "PhP(%)": 21,
    "Flutter(%)": 47,
    "React(%)": 47,
    "Swift(%)": 25,
    "TypeScript(%)": 44,
    "Matlab(%)": 41
  },
  {
    "Month": "2021-09",
    "Python(%)": 62,
    "JavaScript(%)": 28,
    "Java(%)": 13,
    "C#(%)": 33,
    "PhP(%)": 21,
    "Flutter(%)": 49,
    "React(%)": 48,
    "Swift(%)": 23,
    "TypeScript(%)": 47,
    "Matlab(%)": 52
  },
  {
    "Month": "2021-10",
    "Python(%)": 66,
    "JavaScript(%)": 28,
    "Java(%)": 13,
    "C#(%)": 32,
    "PhP(%)": 21,
    "Flutter(%)": 48,
    "React(%)": 51,
    "Swift(%)": 23,
    "TypeScript(%)": 47,
    "Matlab(%)": 55
  },
  {
    "Month": "2021-11",
    "Python(%)": 66,
    "JavaScript(%)": 31,
    "Java(%)": 13,
    "C#(%)": 33,
    "PhP(%)": 20,
    "Flutter(%)": 51,
    "React(%)": 54,
    "Swift(%)": 41,
    "TypeScript(%)": 49,
    "Matlab(%)": 54
  },
  {
    "Month": "2021-12",
    "Python(%)": 64,
    "JavaScript(%)": 28,
    "Java(%)": 13,
    "C#(%)": 31,
    "PhP(%)": 20,
    "Flutter(%)": 49,
    "React(%)": 52,
    "Swift(%)": 27,
    "TypeScript(%)": 47,
    "Matlab(%)": 50
  },
  {
    "Month": "2022-01",
    "Python(%)": 84,
    "JavaScript(%)": 39,
    "Java(%)": 15,
    "C#(%)": 38,
    "PhP(%)": 25,
    "Flutter(%)": 77,
    "React(%)": 73,
    "Swift(%)": 29,
    "TypeScript(%)": 68,
    "Matlab(%)": 67
  },
  {
    "Month": "2022-02",
    "Python(%)": 93,
    "JavaScript(%)": 46,
    "Java(%)": 17,
    "C#(%)": 43,
    "PhP(%)": 30,
    "Flutter(%)": 91,
    "React(%)": 87,
    "Swift(%)": 45,
    "TypeScript(%)": 81,
    "Matlab(%)": 78
  },
  {
    "Month": "2022-03",
    "Python(%)": 100,
    "JavaScript(%)": 47,
    "Java(%)": 19,
    "C#(%)": 45,
    "PhP(%)": 26,
    "Flutter(%)": 94,
    "React(%)": 92,
    "Swift(%)": 29,
    "TypeScript(%)": 84,
    "Matlab(%)": 88
  },
  {
    "Month": "2022-04",
    "Python(%)": 99,
    "JavaScript(%)": 47,
    "Java(%)": 17,
    "C#(%)": 45,
    "PhP(%)": 24,
    "Flutter(%)": 90,
    "React(%)": 98,
    "Swift(%)": 31,
    "TypeScript(%)": 92,
    "Matlab(%)": 100
  },
  {
    "Month": "2022-05",
    "Python(%)": 92,
    "JavaScript(%)": 44,
    "Java(%)": 17,
    "C#(%)": 40,
    "PhP(%)": 22,
    "Flutter(%)": 88,
    "React(%)": 96,
    "Swift(%)": 29,
    "TypeScript(%)": 81,
    "Matlab(%)": 87
  },
  {
    "Month": "2022-06",
    "Python(%)": 90,
    "JavaScript(%)": 45,
    "Java(%)": 16,
    "C#(%)": 41,
    "PhP(%)": 22,
    "Flutter(%)": 92,
    "React(%)": 97,
    "Swift(%)": 28,
    "TypeScript(%)": 86,
    "Matlab(%)": 78
  },
  {
    "Month": "2022-07",
    "Python(%)": 87,
    "JavaScript(%)": 41,
    "Java(%)": 16,
    "C#(%)": 37,
    "PhP(%)": 20,
    "Flutter(%)": 88,
    "React(%)": 92,
    "Swift(%)": 28,
    "TypeScript(%)": 97,
    "Matlab(%)": 81
  },
  {
    "Month": "2022-08",
    "Python(%)": 89,
    "JavaScript(%)": 42,
    "Java(%)": 16,
    "C#(%)": 38,
    "PhP(%)": 20,
    "Flutter(%)": 89,
    "React(%)": 92,
    "Swift(%)": 31,
    "TypeScript(%)": 91,
    "Matlab(%)": 81
  },
  {
    "Month": "2022-09",
    "Python(%)": 93,
    "JavaScript(%)": 45,
    "Java(%)": 18,
    "C#(%)": 40,
    "PhP(%)": 21,
    "Flutter(%)": 89,
    "React(%)": 90,
    "Swift(%)": 30,
    "TypeScript(%)": 88,
    "Matlab(%)": 89
  },
  {
    "Month": "2022-10",
    "Python(%)": 94,
    "JavaScript(%)": 45,
    "Java(%)": 17,
    "C#(%)": 39,
    "PhP(%)": 19,
    "Flutter(%)": 82,
    "React(%)": 91,
    "Swift(%)": 42,
    "TypeScript(%)": 86,
    "Matlab(%)": 93
  },
  {
    "Month": "2022-11",
    "Python(%)": 99,
    "JavaScript(%)": 44,
    "Java(%)": 17,
    "C#(%)": 40,
    "PhP(%)": 20,
    "Flutter(%)": 89,
    "React(%)": 91,
    "Swift(%)": 51,
    "TypeScript(%)": 91,
    "Matlab(%)": 91
  },
  {
    "Month": "2022-12",
    "Python(%)": 86,
    "JavaScript(%)": 41,
    "Java(%)": 15,
    "C#(%)": 36,
    "PhP(%)": 19,
    "Flutter(%)": 91,
    "React(%)": 88,
    "Swift(%)": 34,
    "TypeScript(%)": 84,
    "Matlab(%)": 88
  },
  {
    "Month": "2023-01",
    "Python(%)": 87,
    "JavaScript(%)": 42,
    "Java(%)": 15,
    "C#(%)": 37,
    "PhP(%)": 19,
    "Flutter(%)": 100,
    "React(%)": 91,
    "Swift(%)": 32,
    "TypeScript(%)": 91,
    "Matlab(%)": 75
  },
  {
    "Month": "2023-02",
    "Python(%)": 99,
    "JavaScript(%)": 46,
    "Java(%)": 17,
    "C#(%)": 39,
    "PhP(%)": 20,
    "Flutter(%)": 97,
    "React(%)": 98,
    "Swift(%)": 33,
    "TypeScript(%)": 100,
    "Matlab(%)": 87
  },
  {
    "Month": "2023-03",
    "Python(%)": 91,
    "JavaScript(%)": 45,
    "Java(%)": 17,
    "C#(%)": 40,
    "PhP(%)": 19,
    "Flutter(%)": 91,
    "React(%)": 100,
    "Swift(%)": 40,
    "TypeScript(%)": 97,
    "Matlab(%)": 81
  },
  {
    "Month": "2023-04",
    "Python(%)": 83,
    "JavaScript(%)": 38,
    "Java(%)": 14,
    "C#(%)": 33,
    "PhP(%)": 18,
    "Flutter(%)": 84,
    "React(%)": 86,
    "Swift(%)": 48,
    "TypeScript(%)": 81,
    "Matlab(%)": 79
  },
  {
    "Month": "2023-05",
    "Python(%)": 80,
    "JavaScript(%)": 38,
    "Java(%)": 15,
    "C#(%)": 32,
    "PhP(%)": 18,
    "Flutter(%)": 92,
    "React(%)": 93,
    "Swift(%)": 54,
    "TypeScript(%)": 84,
    "Matlab(%)": 79
  },
  {
    "Month": "2023-06",
    "Python(%)": 81,
    "JavaScript(%)": 39,
    "Java(%)": 15,
    "C#(%)": 32,
    "PhP(%)": 19,
    "Flutter(%)": 87,
    "React(%)": 89,
    "Swift(%)": 66,
    "TypeScript(%)": 85,
    "Matlab(%)": 84
  },
  {
    "Month": "2023-07",
    "Python(%)": 79,
    "JavaScript(%)": 39,
    "Java(%)": 14,
    "C#(%)": 33,
    "PhP(%)": 19,
    "Flutter(%)": 89,
    "React(%)": 88,
    "Swift(%)": 70,
    "TypeScript(%)": 86,
    "Matlab(%)": 71
  },
  {
    "Month": "2023-08",
    "Python(%)": 78,
    "JavaScript(%)": 37,
    "Java(%)": 14,
    "C#(%)": 33,
    "PhP(%)": 18,
    "Flutter(%)": 87,
    "React(%)": 87,
    "Swift(%)": 61,
    "TypeScript(%)": 88,
    "Matlab(%)": 69
  },
  {
    "Month": "2023-09",
    "Python(%)": 83,
    "JavaScript(%)": 34,
    "Java(%)": 14,
    "C#(%)": 33,
    "PhP(%)": 18,
    "Flutter(%)": 86,
    "React(%)": 85,
    "Swift(%)": 74,
    "TypeScript(%)": 85,
    "Matlab(%)": 74
  },
  {
    "Month": "2023-10",
    "Python(%)": 86,
    "JavaScript(%)": 33,
    "Java(%)": 15,
    "C#(%)": 33,
    "PhP(%)": 18,
    "Flutter(%)": 81,
    "React(%)": 84,
    "Swift(%)": 78,
    "TypeScript(%)": 79,
    "Matlab(%)": 73
  },
  {
    "Month": "2023-11",
    "Python(%)": 81,
    "JavaScript(%)": 35,
    "Java(%)": 14,
    "C#(%)": 32,
    "PhP(%)": 19,
    "Flutter(%)": 83,
    "React(%)": 83,
    "Swift(%)": 77,
    "TypeScript(%)": 82,
    "Matlab(%)": 72
  },
  {
    "Month": "2023-12",
    "Python(%)": 72,
    "JavaScript(%)": 33,
    "Java(%)": 13,
    "C#(%)": 29,
    "PhP(%)": 17,
    "Flutter(%)": 81,
    "React(%)": 73,
    "Swift(%)": 66,
    "TypeScript(%)": 70,
    "Matlab(%)": 75
  },
  {
    "Month": "2024-01",
    "Python(%)": 81,
    "JavaScript(%)": 36,
    "Java(%)": 14,
    "C#(%)": 31,
    "PhP(%)": 18,
    "Flutter(%)": 86,
    "React(%)": 89,
    "Swift(%)": 65,
    "TypeScript(%)": 79,
    "Matlab(%)": 71
  },
  {
    "Month": "2024-02",
    "Python(%)": 89,
    "JavaScript(%)": 40,
    "Java(%)": 16,
    "C#(%)": 35,
    "PhP(%)": 18,
    "Flutter(%)": 96,
    "React(%)": 98,
    "Swift(%)": 100,
    "TypeScript(%)": 88,
    "Matlab(%)": 74
  },
  {
    "Month": "2024-03",
    "Python(%)": 86,
    "JavaScript(%)": 38,
    "Java(%)": 15,
    "C#(%)": 34,
    "PhP(%)": 19,
    "Flutter(%)": 90,
    "React(%)": 91,
    "Swift(%)": 59,
    "TypeScript(%)": 85,
    "Matlab(%)": 71
  },
  {
    "Month": "2024-04",
    "Python(%)": 85,
    "JavaScript(%)": 36,
    "Java(%)": 14,
    "C#(%)": 32,
    "PhP(%)": 19,
    "Flutter(%)": 86,
    "React(%)": 97,
    "Swift(%)": 77,
    "TypeScript(%)": 86,
    "Matlab(%)": 70
  },
  {
    "Month": "2024-05",
    "Python(%)": 80,
    "JavaScript(%)": 36,
    "Java(%)": 14,
    "C#(%)": 32,
    "PhP(%)": 18,
    "Flutter(%)": 92,
    "React(%)": 96,
    "Swift(%)": 61,
    "TypeScript(%)": 80,
    "Matlab(%)": 69
  },
  {
    "Month": "2024-06",
    "Python(%)": 76,
    "JavaScript(%)": 32,
    "Java(%)": 14,
    "C#(%)": 30,
    "PhP(%)": 18,
    "Flutter(%)": 84,
    "React(%)": 87,
    "Swift(%)": 61,
    "TypeScript(%)": 76,
    "Matlab(%)": 67
  },
  {
    "Month": "2024-07",
    "Python(%)": 75,
    "JavaScript(%)": 33,
    "Java(%)": 14,
    "C#(%)": 29,
    "PhP(%)": 17,
    "Flutter(%)": 84,
    "React(%)": 92,
    "Swift(%)": 55,
    "TypeScript(%)": 80,
    "Matlab(%)": 65
  },
  {
    "Month": "2024-08",
    "Python(%)": 71,
    "JavaScript(%)": 31,
    "Java(%)": 13,
    "C#(%)": 27,
    "PhP(%)": 18,
    "Flutter(%)": 82,
    "React(%)": 86,
    "Swift(%)": 58,
    "TypeScript(%)": 76,
    "Matlab(%)": 65
  },
  {
    "Month": "2024-09",
    "Python(%)": 79,
    "JavaScript(%)": 31,
    "Java(%)": 13,
    "C#(%)": 27,
    "PhP(%)": 19,
    "Flutter(%)": 79,
    "React(%)": 85,
    "Swift(%)": 59,
    "TypeScript(%)": 73,
    "Matlab(%)": 71
  }
]